MANIFEST.in
README
requirements.txt
setup.py
ajenti.plugin.hosts.egg-info/PKG-INFO
ajenti.plugin.hosts.egg-info/SOURCES.txt
ajenti.plugin.hosts.egg-info/dependency_links.txt
ajenti.plugin.hosts.egg-info/top_level.txt
ajenti_plugin_hosts/.gitignore
ajenti_plugin_hosts/README.md
ajenti_plugin_hosts/__init__.py
ajenti_plugin_hosts/main.py
ajenti_plugin_hosts/plugin.yml
ajenti_plugin_hosts/requirements.txt
ajenti_plugin_hosts/views.py
ajenti_plugin_hosts/locale/af/LC_MESSAGES/app.js
ajenti_plugin_hosts/locale/af/LC_MESSAGES/app.po
ajenti_plugin_hosts/locale/ar/LC_MESSAGES/app.js
ajenti_plugin_hosts/locale/ar/LC_MESSAGES/app.po
ajenti_plugin_hosts/locale/be/LC_MESSAGES/app.js
ajenti_plugin_hosts/locale/be/LC_MESSAGES/app.po
ajenti_plugin_hosts/locale/bg/LC_MESSAGES/app.js
ajenti_plugin_hosts/locale/bg/LC_MESSAGES/app.po
ajenti_plugin_hosts/locale/bn/LC_MESSAGES/app.js
ajenti_plugin_hosts/locale/bn/LC_MESSAGES/app.po
ajenti_plugin_hosts/locale/bs/LC_MESSAGES/app.js
ajenti_plugin_hosts/locale/bs/LC_MESSAGES/app.po
ajenti_plugin_hosts/locale/ca/LC_MESSAGES/app.js
ajenti_plugin_hosts/locale/ca/LC_MESSAGES/app.po
ajenti_plugin_hosts/locale/cs/LC_MESSAGES/app.js
ajenti_plugin_hosts/locale/cs/LC_MESSAGES/app.po
ajenti_plugin_hosts/locale/da/LC_MESSAGES/app.js
ajenti_plugin_hosts/locale/da/LC_MESSAGES/app.po
ajenti_plugin_hosts/locale/de/LC_MESSAGES/app.js
ajenti_plugin_hosts/locale/de/LC_MESSAGES/app.po
ajenti_plugin_hosts/locale/el/LC_MESSAGES/app.js
ajenti_plugin_hosts/locale/el/LC_MESSAGES/app.po
ajenti_plugin_hosts/locale/en/LC_MESSAGES/app.po
ajenti_plugin_hosts/locale/eo/LC_MESSAGES/app.js
ajenti_plugin_hosts/locale/eo/LC_MESSAGES/app.po
ajenti_plugin_hosts/locale/es-ES/LC_MESSAGES/app.js
ajenti_plugin_hosts/locale/es-ES/LC_MESSAGES/app.po
ajenti_plugin_hosts/locale/et/LC_MESSAGES/app.js
ajenti_plugin_hosts/locale/et/LC_MESSAGES/app.po
ajenti_plugin_hosts/locale/fa/LC_MESSAGES/app.js
ajenti_plugin_hosts/locale/fa/LC_MESSAGES/app.po
ajenti_plugin_hosts/locale/fi/LC_MESSAGES/app.js
ajenti_plugin_hosts/locale/fi/LC_MESSAGES/app.po
ajenti_plugin_hosts/locale/fr/LC_MESSAGES/app.js
ajenti_plugin_hosts/locale/fr/LC_MESSAGES/app.po
