Metadata-Version: 1.2
Name: ajenti.plugin.hosts
Version: 0.1
Summary: hosts
Home-page: https://ajenti.org
Author: Arnaud Kientz
Author-email: arnaud@unpeud.info
License: UNKNOWN
Platform: UNKNOWN
Requires-Python: >=3
